meshcore_cli/__init__.py
meshcore_cli/__main__.py
meshcore_cli/meshcore_cli.py
meshcore_cli-1.3.13.dist-info/METADATA
meshcore_cli-1.3.13.dist-info/WHEEL
meshcore_cli-1.3.13.dist-info/entry_points.txt
meshcore_cli-1.3.13.dist-info/licenses/LICENSE
meshcore_cli-1.3.13.dist-info/RECORD
