Metadata-Version: 2.4
Name: meshcore-cli
Version: 1.3.13
Summary: Command line interface to meshcore companion radios
Project-URL: Homepage, https://github.com/fdlamotte/meshcore-cli
Project-URL: Issues, https://github.com/fdlamotte/meshcore-cli/issues
Author-email: Florent de Lamotte <florent@frizoncorrea.fr>
License-Expression: MIT
License-File: LICENSE
Classifier: Operating System :: OS Independent
Classifier: Programming Language :: Python :: 3
Requires-Python: >=3.10
Requires-Dist: bleak<2.0,>=0.22
Requires-Dist: meshcore>=2.2.3
Requires-Dist: prompt-toolkit>=3.0.50
Requires-Dist: pycryptodome
Requires-Dist: requests>=2.28.0
